setup.py
dexonlineBK/__init__.py
dexonlineBK/dexonlineBK.py
dexonlineBK/loc_flexiuni_6_0.py
dexonlineBK.egg-info/PKG-INFO
dexonlineBK.egg-info/SOURCES.txt
dexonlineBK.egg-info/dependency_links.txt
dexonlineBK.egg-info/not-zip-safe
dexonlineBK.egg-info/top_level.txt