Metadata-Version: 1.0
Name: dexonlineBK
Version: 0.0.2
Summary: Small dexonline.ro API for Python
Home-page: UNKNOWN
Author: Alexandru Petrachi (BlackKakapo)
Author-email: UNKNOWN
License: UNKNOWN
Platform: UNKNOWN
